{
  "sections": {
    "43fa649e-5001-458e-b0f4-8ab29098a055": {
      "type": "hero",
      "blocks": {
        "template--15907127984325__43fa649e-5001-458e-b0f4-8ab29098a055-166783048692bbddc1-0": {
          "type": "fullwidth",
          "settings": {
            "external_video": "",
            "disable_autoplay_on_mobile": true,
            "description": "",
            "image": "shopify:\/\/shop_images\/1.png",
            "image_mobile": "shopify:\/\/shop_images\/Gold_Shimmer_Glitter_Aesthetic_Sale_Website_Banner_Instagram_Story.png",
            "image_crop": "center",
            "background_overlay": "#fffdfd",
            "background_overlay_opacity": 22,
            "align_vertical": "bottom",
            "align_horizontal": "center",
            "show_background": false,
            "subheading": "",
            "heading": "<p><em><strong>False Lashes Subscription<\/strong><\/em><\/p>",
            "paragraph": "<p>Sign up for your monthly delivery<\/p>",
            "button_style_1": "solid",
            "button_size_1": "m",
            "button_text_1": "Sign Up",
            "button_url_1": "shopify:\/\/collections\/all",
            "button_style_2": "outline",
            "button_size_2": "m",
            "button_text_2": "",
            "button_url_2": ""
          }
        }
      },
      "block_order": [
        "template--15907127984325__43fa649e-5001-458e-b0f4-8ab29098a055-166783048692bbddc1-0"
      ],
      "settings": {
        "style": "style-1",
        "spacing_desktop": "mt-0--large mb-0--large",
        "spacing_mobile": "mt-0 mb-0",
        "height": "viewport",
        "autoplay": false,
        "autoplay_speed": 5
      }
    },
    "03d54d72-e46a-473d-bb02-c2da979392cd": {
      "type": "richtext",
      "blocks": {
        "template--15907127984325__03d54d72-e46a-473d-bb02-c2da979392cd-16678305518bb1395f-0": {
          "type": "subheading",
          "settings": {
            "subheading": "How does it work?"
          }
        },
        "template--15907127984325__03d54d72-e46a-473d-bb02-c2da979392cd-16678305518bb1395f-1": {
          "type": "heading",
          "settings": {
            "heading": "<p>Luxurious lashes delivered to your door<\/p>"
          }
        },
        "template--15907127984325__03d54d72-e46a-473d-bb02-c2da979392cd-16678305518bb1395f-3": {
          "type": "buttons",
          "settings": {
            "button_style_1": "link",
            "button_size_1": "m",
            "button_text_1": "FAQs",
            "button_url_1": "shopify:\/\/collections",
            "button_style_2": "link",
            "button_size_2": "m",
            "button_text_2": "",
            "button_url_2": ""
          }
        },
        "template--15907127984325__03d54d72-e46a-473d-bb02-c2da979392cd-16678305518bb1395f-2": {
          "type": "paragraph",
          "settings": {
            "paragraph": "<p>We offer a convenient subscription service where you can choose to receive lashes of your choice in style delivered to your door each month. It's the perfect way to always have a fresh supply of gorgeous, long-lasting lashes.<\/p><p><\/p><p>We specialize in high-quality false eyelashes. Our lashes are handmade with the finest materials, ensuring that they are comfortable to wear and look natural on your eyes.<\/p>"
          }
        }
      },
      "block_order": [
        "template--15907127984325__03d54d72-e46a-473d-bb02-c2da979392cd-16678305518bb1395f-0",
        "template--15907127984325__03d54d72-e46a-473d-bb02-c2da979392cd-16678305518bb1395f-1",
        "template--15907127984325__03d54d72-e46a-473d-bb02-c2da979392cd-16678305518bb1395f-3",
        "template--15907127984325__03d54d72-e46a-473d-bb02-c2da979392cd-16678305518bb1395f-2"
      ],
      "settings": {
        "style": "style-2",
        "spacing_desktop": "mt-0--large mb-0--large",
        "spacing_mobile": "mt-0 mb-0",
        "text_align": "center"
      }
    },
    "4e185abc-b3c0-47ef-8eb1-e6417ee0b89a": {
      "type": "featured-products",
      "settings": {
        "style": "style-1",
        "spacing_desktop": "mt-0--large mb-0--large",
        "spacing_mobile": "mt-0 mb-0",
        "layout": "slider-right",
        "subheading": "Our styles",
        "heading": "<p>Choose your perfect pair &lt;3<\/p>",
        "paragraph": "<p>Mix & match!<\/p>",
        "button_style_1": "solid",
        "button_size_1": "m",
        "button_text_1": "Shop now",
        "button_url_1": "shopify:\/\/collections",
        "collection": "",
        "product_list": [

        ],
        "products_count": 8,
        "autoplay": false,
        "autoplay_speed": 5
      }
    },
    "6d9fa46b-784c-4fa8-a2cf-2b5f7d428352": {
      "type": "marquee",
      "settings": {
        "style": "style-3",
        "spacing_desktop": "mt-0--large mb-0--large",
        "spacing_mobile": "mt-0 mb-0",
        "marquee_text": "<p>Sign up for a Lyngsy subscription today and experience the ultimate in lash luxury <\/p>",
        "marquee_position": "top",
        "marquee_pause_on_hover": true,
        "marquee_speed": 1,
        "remove_image_gap": false,
        "image_aspect_ratio": "1-1"
      }
    },
    "82a922ed-87db-466a-b638-32d73e3cfebc": {
      "type": "featured-content-columns",
      "blocks": {
        "template--15907127984325__82a922ed-87db-466a-b638-32d73e3cfebc-16678305328fa4bc7a-0": {
          "type": "big-card",
          "settings": {
            "subheading": "",
            "heading": "<p>Heading <em>with accent <\/em><em><strong>element<\/strong><\/em><\/p>",
            "paragraph": "<p>Use this text to share information about your store with your customers. Describe products, share announcements, or welcome customers to your store.<\/p>",
            "button_style_1": "solid",
            "button_size_1": "m",
            "button_text_1": "Learn More",
            "button_url_1": "shopify:\/\/collections\/all",
            "button_style_2": "solid",
            "button_size_2": "s",
            "button_text_2": "",
            "button_url_2": ""
          }
        },
        "template--15907127984325__82a922ed-87db-466a-b638-32d73e3cfebc-16678305328fa4bc7a-1": {
          "type": "small-card",
          "settings": {
            "subheading": "",
            "heading": "<p>Heading <em>with accent <\/em><em><strong>element<\/strong><\/em><\/p>",
            "paragraph": "<p>Use this text to share information about your store with your customers. Describe products, share announcements, or welcome customers to your store.<\/p>",
            "button_style_1": "outline",
            "button_size_1": "m",
            "button_text_1": "Learn More",
            "button_url_1": "shopify:\/\/collections\/all",
            "button_style_2": "solid",
            "button_size_2": "s",
            "button_text_2": "",
            "button_url_2": ""
          }
        }
      },
      "block_order": [
        "template--15907127984325__82a922ed-87db-466a-b638-32d73e3cfebc-16678305328fa4bc7a-0",
        "template--15907127984325__82a922ed-87db-466a-b638-32d73e3cfebc-16678305328fa4bc7a-1"
      ],
      "settings": {
        "style": "style-1",
        "spacing_desktop": "mt-0--large mb-0--large",
        "spacing_mobile": "mt-0 mb-0"
      }
    },
    "f68c224f-3d8b-46a9-8a25-915995370bee": {
      "type": "image-with-text",
      "blocks": {
        "template--15907127984325__f68c224f-3d8b-46a9-8a25-915995370bee-1667830550325d52b8-0": {
          "type": "subheading",
          "settings": {
            "subheading": "Tell your story"
          }
        },
        "template--15907127984325__f68c224f-3d8b-46a9-8a25-915995370bee-1667830550325d52b8-1": {
          "type": "heading",
          "settings": {
            "heading": "<p>Talk about <em>your brand<\/em><\/p>"
          }
        },
        "template--15907127984325__f68c224f-3d8b-46a9-8a25-915995370bee-1667830550325d52b8-2": {
          "type": "paragraph",
          "settings": {
            "paragraph": "<p>Share information about your brand with your customers. Describe a product, make announcements, or welcome customers to your store.<\/p>"
          }
        },
        "template--15907127984325__f68c224f-3d8b-46a9-8a25-915995370bee-1667830550325d52b8-3": {
          "type": "buttons",
          "settings": {
            "button_style_1": "solid",
            "button_size_1": "m",
            "button_text_1": "Discover More",
            "button_url_1": "\/",
            "button_style_2": "link",
            "button_size_2": "m",
            "button_text_2": "",
            "button_url_2": ""
          }
        }
      },
      "block_order": [
        "template--15907127984325__f68c224f-3d8b-46a9-8a25-915995370bee-1667830550325d52b8-0",
        "template--15907127984325__f68c224f-3d8b-46a9-8a25-915995370bee-1667830550325d52b8-1",
        "template--15907127984325__f68c224f-3d8b-46a9-8a25-915995370bee-1667830550325d52b8-2",
        "template--15907127984325__f68c224f-3d8b-46a9-8a25-915995370bee-1667830550325d52b8-3"
      ],
      "settings": {
        "style": "style-2",
        "spacing_desktop": "mt-0--large mb-0--large",
        "spacing_mobile": "mt-0 mb-0",
        "height": "5-4",
        "enable_fullwidth": true,
        "swap_image_and_text": false,
        "image_crop": "center"
      }
    },
    "07701733-7c04-43b3-825b-dd5a1006fc6c": {
      "type": "image-with-text",
      "blocks": {
        "template--15907127984325__07701733-7c04-43b3-825b-dd5a1006fc6c-1667830550325d52b8-0": {
          "type": "subheading",
          "settings": {
            "subheading": "Tell your story"
          }
        },
        "template--15907127984325__07701733-7c04-43b3-825b-dd5a1006fc6c-1667830550325d52b8-1": {
          "type": "heading",
          "settings": {
            "heading": "<p>Talk about <em>your brand<\/em><\/p>"
          }
        },
        "template--15907127984325__07701733-7c04-43b3-825b-dd5a1006fc6c-1667830550325d52b8-2": {
          "type": "paragraph",
          "settings": {
            "paragraph": "<p>Share information about your brand with your customers. Describe a product, make announcements, or welcome customers to your store.<\/p>"
          }
        },
        "template--15907127984325__07701733-7c04-43b3-825b-dd5a1006fc6c-1667830550325d52b8-3": {
          "type": "buttons",
          "settings": {
            "button_style_1": "solid",
            "button_size_1": "m",
            "button_text_1": "Discover More",
            "button_url_1": "\/",
            "button_style_2": "link",
            "button_size_2": "m",
            "button_text_2": "",
            "button_url_2": ""
          }
        }
      },
      "block_order": [
        "template--15907127984325__07701733-7c04-43b3-825b-dd5a1006fc6c-1667830550325d52b8-0",
        "template--15907127984325__07701733-7c04-43b3-825b-dd5a1006fc6c-1667830550325d52b8-1",
        "template--15907127984325__07701733-7c04-43b3-825b-dd5a1006fc6c-1667830550325d52b8-2",
        "template--15907127984325__07701733-7c04-43b3-825b-dd5a1006fc6c-1667830550325d52b8-3"
      ],
      "settings": {
        "style": "style-1",
        "spacing_desktop": "mt-0--large mb-0--large",
        "spacing_mobile": "mt-0 mb-0",
        "height": "5-4",
        "enable_fullwidth": true,
        "swap_image_and_text": true,
        "image_crop": "center"
      }
    },
    "453e83ba-c6dc-41a8-a5a0-e923b1194687": {
      "type": "featured-collections",
      "blocks": {
        "template--15907127984325__453e83ba-c6dc-41a8-a5a0-e923b1194687-1667830533495cec03-0": {
          "type": "card",
          "settings": {
            "collection": "",
            "heading": "Collection",
            "link_text": "",
            "link_url": "shopify:\/\/collections"
          }
        },
        "template--15907127984325__453e83ba-c6dc-41a8-a5a0-e923b1194687-1667830533495cec03-1": {
          "type": "card",
          "settings": {
            "collection": "",
            "heading": "Collection",
            "link_text": "",
            "link_url": "shopify:\/\/collections"
          }
        },
        "template--15907127984325__453e83ba-c6dc-41a8-a5a0-e923b1194687-1667830533495cec03-2": {
          "type": "card",
          "settings": {
            "collection": "",
            "heading": "Collection",
            "link_text": "",
            "link_url": "shopify:\/\/collections"
          }
        }
      },
      "block_order": [
        "template--15907127984325__453e83ba-c6dc-41a8-a5a0-e923b1194687-1667830533495cec03-0",
        "template--15907127984325__453e83ba-c6dc-41a8-a5a0-e923b1194687-1667830533495cec03-1",
        "template--15907127984325__453e83ba-c6dc-41a8-a5a0-e923b1194687-1667830533495cec03-2"
      ],
      "settings": {
        "style": "style-1",
        "spacing_desktop": "mt-s--large mb-s--large",
        "spacing_mobile": "mt-s mb-s",
        "text_align": "left",
        "subheading": "",
        "heading": "<p>Collections <em><strong>Headline<\/strong><\/em><\/p>",
        "paragraph": "<p>Add a short description for your collections<\/p>",
        "media_type": "portrait",
        "card_content_layout": "outside",
        "show_cards_background": false,
        "items_per_slide": 3
      }
    },
    "c7cb7b4b-7c31-4101-8698-07ac564c27d2": {
      "type": "featured-collection",
      "settings": {
        "style": "style-1",
        "spacing_desktop": "mt-s--large mb-s--large",
        "spacing_mobile": "mt-s mb-s",
        "layout_desktop": "slider-right",
        "layout_mobile": "image-top",
        "image_crop": "center",
        "subheading": "",
        "heading": "<p>Featured <em>collection<\/em><\/p>",
        "paragraph": "<p>Pair text with an image to focus on your collection. Add details on availability, style, or even provide a review.<\/p>",
        "button_style": "link",
        "button_size": "m",
        "button_text": "",
        "button_url_1": "",
        "collection": "",
        "products_count": 12,
        "autoplay": false,
        "autoplay_speed": 5
      }
    },
    "0e1a2307-29a4-479c-92cc-d6d30fbace10": {
      "type": "banner",
      "blocks": {
        "template--15907127984325__0e1a2307-29a4-479c-92cc-d6d30fbace10-166783053284ee5819-0": {
          "type": "subheading",
          "settings": {
            "subheading": "Add a tagline"
          }
        },
        "template--15907127984325__0e1a2307-29a4-479c-92cc-d6d30fbace10-166783053284ee5819-1": {
          "type": "heading",
          "settings": {
            "heading": "<p>Promotional <em><strong>banner<\/strong><\/em><\/p>"
          }
        },
        "template--15907127984325__0e1a2307-29a4-479c-92cc-d6d30fbace10-166783053284ee5819-2": {
          "type": "buttons",
          "settings": {
            "button_style_1": "solid",
            "button_size_1": "m",
            "button_text_1": "Explore",
            "button_url_1": "shopify:\/\/collections",
            "button_style_2": "solid",
            "button_size_2": "m",
            "button_text_2": "",
            "button_url_2": ""
          }
        }
      },
      "block_order": [
        "template--15907127984325__0e1a2307-29a4-479c-92cc-d6d30fbace10-166783053284ee5819-0",
        "template--15907127984325__0e1a2307-29a4-479c-92cc-d6d30fbace10-166783053284ee5819-1",
        "template--15907127984325__0e1a2307-29a4-479c-92cc-d6d30fbace10-166783053284ee5819-2"
      ],
      "settings": {
        "style": "style-1",
        "spacing_desktop": "mt-0--large mb-0--large",
        "spacing_mobile": "mt-0 mb-0",
        "height": "medium",
        "image_crop": "center",
        "background_overlay": "#000000",
        "background_overlay_opacity": 0,
        "show_background": false,
        "align_vertical": "center",
        "align_horizontal": "left"
      }
    },
    "d334f4c8-4f23-4067-999f-22c4784e6396": {
      "type": "promo-bar",
      "settings": {
        "style": "style-2",
        "spacing_desktop": "mt-0--large mb-0--large",
        "spacing_mobile": "mt-0 mb-0",
        "layout": "justify",
        "heading": "Promo text",
        "paragraph": "<p>Promo Text Conditions<\/p>",
        "button_style_1": "outline",
        "button_size_1": "s",
        "button_text_1": "Learn More",
        "button_url_1": "\/",
        "button_style_2": "solid",
        "button_size_2": "s",
        "button_text_2": "Shop Now",
        "button_url_2": "shopify:\/\/collections"
      }
    },
    "93e60874-84d5-415c-9bba-85aa4dd63719": {
      "type": "banner",
      "blocks": {
        "template--15907127984325__93e60874-84d5-415c-9bba-85aa4dd63719-166783053284ee5819-0": {
          "type": "subheading",
          "settings": {
            "subheading": "Add a tagline"
          }
        },
        "template--15907127984325__93e60874-84d5-415c-9bba-85aa4dd63719-166783053284ee5819-1": {
          "type": "heading",
          "settings": {
            "heading": "<p>Promotional <em><strong>banner<\/strong><\/em><\/p>"
          }
        },
        "template--15907127984325__93e60874-84d5-415c-9bba-85aa4dd63719-166783053284ee5819-2": {
          "type": "buttons",
          "settings": {
            "button_style_1": "solid",
            "button_size_1": "m",
            "button_text_1": "Explore",
            "button_url_1": "shopify:\/\/collections",
            "button_style_2": "solid",
            "button_size_2": "m",
            "button_text_2": "",
            "button_url_2": ""
          }
        }
      },
      "block_order": [
        "template--15907127984325__93e60874-84d5-415c-9bba-85aa4dd63719-166783053284ee5819-0",
        "template--15907127984325__93e60874-84d5-415c-9bba-85aa4dd63719-166783053284ee5819-1",
        "template--15907127984325__93e60874-84d5-415c-9bba-85aa4dd63719-166783053284ee5819-2"
      ],
      "settings": {
        "style": "style-1",
        "spacing_desktop": "mt-0--large mb-0--large",
        "spacing_mobile": "mt-0 mb-0",
        "height": "medium",
        "image_crop": "center",
        "background_overlay": "#000000",
        "background_overlay_opacity": 0,
        "show_background": false,
        "align_vertical": "center",
        "align_horizontal": "right"
      }
    },
    "6e71800e-22a3-457f-b902-ffa51664b1af": {
      "type": "section-shop-module",
      "blocks": {
        "template--15907127984325__6e71800e-22a3-457f-b902-ffa51664b1af-16678307882edb75e3-0": {
          "type": "hotspot",
          "settings": {
            "product": "",
            "x_position": 22,
            "y_position": 41
          }
        },
        "template--15907127984325__6e71800e-22a3-457f-b902-ffa51664b1af-16678307882edb75e3-1": {
          "type": "hotspot",
          "settings": {
            "product": "",
            "x_position": 51,
            "y_position": 65
          }
        },
        "template--15907127984325__6e71800e-22a3-457f-b902-ffa51664b1af-16678307882edb75e3-2": {
          "type": "hotspot",
          "settings": {
            "product": "",
            "x_position": 75,
            "y_position": 40
          }
        }
      },
      "block_order": [
        "template--15907127984325__6e71800e-22a3-457f-b902-ffa51664b1af-16678307882edb75e3-0",
        "template--15907127984325__6e71800e-22a3-457f-b902-ffa51664b1af-16678307882edb75e3-1",
        "template--15907127984325__6e71800e-22a3-457f-b902-ffa51664b1af-16678307882edb75e3-2"
      ],
      "settings": {
        "style": "style-1",
        "spacing_desktop": "mt-0--large mb-0--large",
        "spacing_mobile": "mt-0 mb-0",
        "hotspot_color": "#fff",
        "swap_layout": false,
        "subheading": "",
        "heading": "<p>Look Heading<\/p>",
        "paragraph": "<p>Showcase a look build from different products in the store.<\/p>",
        "button_style_1": "link",
        "button_size_1": "m",
        "button_text_1": "",
        "button_url_1": ""
      }
    },
    "2ff801b9-2c09-4c72-bccc-dd330e1cdf87": {
      "type": "featured-blog",
      "settings": {
        "style": "style-3",
        "spacing_desktop": "mt-0--large mb-0--large",
        "spacing_mobile": "mt-0 mb-0",
        "layout": "slider-right",
        "subheading": "Add a tagline",
        "heading": "<p>Latest <em><strong>news<\/strong><\/em><\/p>",
        "paragraph": "",
        "button_style_1": "link",
        "button_size_1": "s",
        "button_text_1": "Explore",
        "button_url_1": "\/",
        "blog": "",
        "articles_count": 12,
        "autoplay": false,
        "autoplay_speed": 5
      }
    },
    "5035fe8c-2acc-40f3-ada0-b62cca12b274": {
      "type": "testimonials",
      "blocks": {
        "template--15907127984325__5035fe8c-2acc-40f3-ada0-b62cca12b274-166783078845514862-0": {
          "type": "testimonial",
          "settings": {
            "rating": 5,
            "heading": "Add a tagline",
            "content": "<p>“Add customer reviews and testimonials to showcase your store’s happy customers.”<\/p>",
            "author": "Author's name"
          }
        },
        "template--15907127984325__5035fe8c-2acc-40f3-ada0-b62cca12b274-166783078845514862-1": {
          "type": "testimonial",
          "settings": {
            "rating": 5,
            "heading": "Add a tagline",
            "content": "<p>“Add customer reviews and testimonials to showcase your store’s happy customers.”<\/p>",
            "author": "Author's name"
          }
        },
        "template--15907127984325__5035fe8c-2acc-40f3-ada0-b62cca12b274-166783078845514862-2": {
          "type": "testimonial",
          "settings": {
            "rating": 5,
            "heading": "Add a tagline",
            "content": "<p>“Add customer reviews and testimonials to showcase your store’s happy customers.”<\/p>",
            "author": "Author's name"
          }
        }
      },
      "block_order": [
        "template--15907127984325__5035fe8c-2acc-40f3-ada0-b62cca12b274-166783078845514862-0",
        "template--15907127984325__5035fe8c-2acc-40f3-ada0-b62cca12b274-166783078845514862-1",
        "template--15907127984325__5035fe8c-2acc-40f3-ada0-b62cca12b274-166783078845514862-2"
      ],
      "settings": {
        "style": "style-1",
        "spacing_desktop": "mt-0--large mb-0--large",
        "spacing_mobile": "mt-0 mb-0",
        "heading": "<p>Talk about <\/p><p><em><strong>your testimonials<\/strong><\/em><\/p>",
        "items_per_slide": 1,
        "autoplay_slider": false,
        "autoplay_speed": 5
      }
    },
    "76fd847c-7a8a-495e-9e1e-57cf30735a61": {
      "type": "social-feed",
      "blocks": {
        "template--15907127984325__76fd847c-7a8a-495e-9e1e-57cf30735a61-166783078807b334d9-0": {
          "type": "image",
          "settings": {
            "link_url": "",
            "hide_on_tablet": false,
            "hide_on_mobile": false
          }
        },
        "template--15907127984325__76fd847c-7a8a-495e-9e1e-57cf30735a61-166783078807b334d9-1": {
          "type": "image",
          "settings": {
            "link_url": "",
            "hide_on_tablet": false,
            "hide_on_mobile": false
          }
        },
        "template--15907127984325__76fd847c-7a8a-495e-9e1e-57cf30735a61-166783078807b334d9-2": {
          "type": "image",
          "settings": {
            "link_url": "",
            "hide_on_tablet": false,
            "hide_on_mobile": false
          }
        },
        "template--15907127984325__76fd847c-7a8a-495e-9e1e-57cf30735a61-166783078807b334d9-3": {
          "type": "image",
          "settings": {
            "link_url": "",
            "hide_on_tablet": false,
            "hide_on_mobile": false
          }
        }
      },
      "block_order": [
        "template--15907127984325__76fd847c-7a8a-495e-9e1e-57cf30735a61-166783078807b334d9-0",
        "template--15907127984325__76fd847c-7a8a-495e-9e1e-57cf30735a61-166783078807b334d9-1",
        "template--15907127984325__76fd847c-7a8a-495e-9e1e-57cf30735a61-166783078807b334d9-2",
        "template--15907127984325__76fd847c-7a8a-495e-9e1e-57cf30735a61-166783078807b334d9-3"
      ],
      "settings": {
        "style": "style-1",
        "spacing_desktop": "mt-0--large mb-0--large",
        "spacing_mobile": "mt-0 mb-0",
        "content_position": "top",
        "subheading": "",
        "heading": "<p>Heading for Social images<\/p>",
        "paragraph": "",
        "button_style_1": "solid",
        "button_size_1": "m",
        "button_text_1": "",
        "button_url_1": "",
        "button_style_2": "solid",
        "button_size_2": "m",
        "button_text_2": "",
        "button_url_2": "",
        "remove_image_gap": false,
        "image_aspect_ratio": "1-1"
      }
    },
    "82e419c8-3746-4f17-9dcf-d3fae1f17e8c": {
      "type": "email-signup-banner",
      "settings": {
        "style": "style-2",
        "spacing_desktop": "mt-0--large mb-0--large",
        "spacing_mobile": "mt-0 mb-0",
        "heading": "<p>Subscribe <em>to newsletter<\/em><\/p>",
        "paragraph": "<p>Add descriptive text to invite your users to sign up for your newsletter.<\/p>"
      }
    }
  },
  "order": [
    "43fa649e-5001-458e-b0f4-8ab29098a055",
    "03d54d72-e46a-473d-bb02-c2da979392cd",
    "4e185abc-b3c0-47ef-8eb1-e6417ee0b89a",
    "6d9fa46b-784c-4fa8-a2cf-2b5f7d428352",
    "82a922ed-87db-466a-b638-32d73e3cfebc",
    "f68c224f-3d8b-46a9-8a25-915995370bee",
    "07701733-7c04-43b3-825b-dd5a1006fc6c",
    "453e83ba-c6dc-41a8-a5a0-e923b1194687",
    "c7cb7b4b-7c31-4101-8698-07ac564c27d2",
    "0e1a2307-29a4-479c-92cc-d6d30fbace10",
    "d334f4c8-4f23-4067-999f-22c4784e6396",
    "93e60874-84d5-415c-9bba-85aa4dd63719",
    "6e71800e-22a3-457f-b902-ffa51664b1af",
    "2ff801b9-2c09-4c72-bccc-dd330e1cdf87",
    "5035fe8c-2acc-40f3-ada0-b62cca12b274",
    "76fd847c-7a8a-495e-9e1e-57cf30735a61",
    "82e419c8-3746-4f17-9dcf-d3fae1f17e8c"
  ]
}
